casanova/__init__.py
casanova/__main__.py
casanova/cli.py
casanova/contiguous_range_set.py
casanova/defaults.py
casanova/enricher.py
casanova/exceptions.py
casanova/headers.py
casanova/http.py
casanova/ndjson.py
casanova/reader.py
casanova/record.py
casanova/resumers.py
casanova/reverse_reader.py
casanova/serialization.py
casanova/types.py
casanova/utils.py
casanova/writer.py
scripts/__init__.py
scripts/generate_readme.py
scripts/http.py
scripts/null_byte_writer_error.py
casanova-2.0.2.dist-info/LICENSE.txt
casanova-2.0.2.dist-info/METADATA
casanova-2.0.2.dist-info/WHEEL
casanova-2.0.2.dist-info/entry_points.txt
casanova-2.0.2.dist-info/top_level.txt
casanova-2.0.2.dist-info/zip-safe
casanova-2.0.2.dist-info/RECORD
