Metadata-Version: 2.1
Name: casanova
Version: 2.0.2
Summary: Specialized & performant CSV readers, writers and enrichers for python.
Home-page: http://github.com/medialab/casanova
Author: Guillaume Plique
Author-email: kropotkinepiotr@gmail.com
License: MIT
Keywords: csv
Platform: UNKNOWN
Requires-Python: >=3.7
Requires-Dist: ebbe (<2,>=1.11.0)
Requires-Dist: typing-extensions ; python_version<'3.11'
Provides-Extra: http
Requires-Dist: urllib3 ; extra == 'http'
Requires-Dist: certifi ; extra == 'http'
